rti/cloud/CliAuth.py
rti/cloud/DatabusParticipant.py
rti/cloud/ManagementCli.py
rti/cloud/__init__.py
rti.cloud-0.2.0.dist-info/METADATA
rti.cloud-0.2.0.dist-info/WHEEL
rti.cloud-0.2.0.dist-info/entry_points.txt
rti.cloud-0.2.0.dist-info/top_level.txt
rti.cloud-0.2.0.dist-info/RECORD
